setup.py
Spitter.egg-info/PKG-INFO
Spitter.egg-info/SOURCES.txt
Spitter.egg-info/dependency_links.txt
Spitter.egg-info/entry_points.txt
Spitter.egg-info/not-zip-safe
Spitter.egg-info/requires.txt
Spitter.egg-info/top_level.txt
spitter/__init__.py
spitter/main.py
spitter/models.py
spitter/test_sqla.py
spitter/tests.py
spitter/views.py