Metadata-Version: 1.1
Name: Spitter
Version: 0.4
Summary: Spitter is a microblogging web app written using the pyramid web framework
Home-page: http://src.serverzen.com/spitter
Author: Rocky Burt
Author-email: rocky@serverzen.com
License: UNKNOWN
Keywords: web wsgi bfg pylons pyramid khufu
Platform: UNKNOWN
Classifier: Development Status :: 3 - Alpha
Classifier: Intended Audience :: Developers
Classifier: Programming Language :: Python
Classifier: Topic :: Internet :: WWW/HTTP :: Dynamic Content
Classifier: Topic :: Internet :: WWW/HTTP :: WSGI :: Application
